sparqlkit/__init__.py
sparqlkit/cli.py
sparqlkit/comments.py
sparqlkit/grammar.lark
sparqlkit/parser.py
sparqlkit/py.typed
sparqlkit/serializer.py
sparqlkit-0.4.1.dist-info/METADATA
sparqlkit-0.4.1.dist-info/WHEEL
sparqlkit-0.4.1.dist-info/entry_points.txt
sparqlkit-0.4.1.dist-info/licenses/LICENSE
sparqlkit-0.4.1.dist-info/RECORD
