Metadata-Version: 2.4
Name: sparqlkit
Version: 0.4.1
Summary: This package provides parsers and serializers for the SPARQL 1.1 Query and Update Language.
Author-email: Edmond Chuc <edmond@kurrawong.ai>
License: MIT
License-File: LICENSE
Requires-Python: >=3.11
Requires-Dist: lark>=1.1.8
Provides-Extra: cli
Requires-Dist: typer>=0.12; extra == 'cli'
